astria/__init__.py
astria/clean.py
astria/cli.py
astria/unsubscribe.py
astria-0.1.dist-info/licenses/LICENSE
astria-0.1.dist-info/METADATA
astria-0.1.dist-info/WHEEL
astria-0.1.dist-info/entry_points.txt
astria-0.1.dist-info/top_level.txt
astria-0.1.dist-info/RECORD
