Metadata-Version: 2.4
Name: astria
Version: 0.1
Summary: Astria is an email cleanup CLI tool that allows for fast deletion and newsletter unsubscribing.
Author: Vallg-333
Author-email: vallg8343@proton.me
License-File: LICENSE
Requires-Dist: click
Requires-Dist: bs4
Dynamic: author
Dynamic: author-email
Dynamic: license-file
Dynamic: requires-dist
Dynamic: summary
